tiles_util/__init__.py
tiles_util/grid/__init__.py
tiles_util/grid/garsgrid.py
tiles_util/grid/geohashgrid.py
tiles_util/grid/georefgrid.py
tiles_util/grid/h3grid.py
tiles_util/grid/h3grid_old.py
tiles_util/grid/h3grid_single.py
tiles_util/grid/hashgrid.py
tiles_util/grid/hexagongrid.py
tiles_util/grid/maidenhead.py
tiles_util/grid/maidenheadgrid.py
tiles_util/grid/maidenheadgrid_old.py
tiles_util/grid/mgrs_100km.py
tiles_util/grid/mgrsgrid.py
tiles_util/grid/mgrsgrid_old.py
tiles_util/grid/pluscodegrid.py
tiles_util/grid/s2grid.py
tiles_util/grid/squaregrid.py
tiles_util/grid/vectortilegrid.py
tiles_util/mbtiles/__init__.py
tiles_util/mbtiles/bounds.py
tiles_util/mbtiles/flipy.py
tiles_util/mbtiles/folder2mbtiles.py
tiles_util/mbtiles/folder2s3.py
tiles_util/mbtiles/geojson2mbtiles.py
tiles_util/mbtiles/geojson2mbtiles_old.py
tiles_util/mbtiles/mbtiles2folder.py
tiles_util/mbtiles/mbtiles2geojson.py
tiles_util/mbtiles/mbtiles2geojson_old.py
tiles_util/mbtiles/mbtiles2geojson_tippecanoe.py
tiles_util/mbtiles/mbtiles2pbf.py
tiles_util/mbtiles/mbtiles2pmtiles.py
tiles_util/mbtiles/mbtiles2s3.py
tiles_util/mbtiles/mbtilescompress.py
tiles_util/mbtiles/mbtilesdecompress.py
tiles_util/mbtiles/mbtilesfixmeta.py
tiles_util/mbtiles/mbtilesinfo.py
tiles_util/mbtiles/mbtilesinspect.py
tiles_util/mbtiles/mbtilesmerge.py
tiles_util/mbtiles/mbtilessplit.py
tiles_util/mbtiles/pbf2geojson.py
tiles_util/mbtiles/pbfinfo.py
tiles_util/osm/__init__.py
tiles_util/osm/geofabrik_sources.py
tiles_util/osm/osm2geojson.py
tiles_util/osm/osmdownload.py
tiles_util/osm/osminfo.py
tiles_util/osm/osmpub.py
tiles_util/osm/osmreplication.py
tiles_util/server/__init__.py
tiles_util/server/servefolder.py
tiles_util/server/servembtiles.py
tiles_util/server/servepmtiles.py
tiles_util/server/servepostgis.py
tiles_util/server/servevectormbtiles.py
tiles_util/test/__init__.py
tiles_util/test/geojson2vt_test.py
tiles_util/test/test.py
tiles_util/test/test2.py
tiles_util/test/test3.py
tiles_util-1.1.0.dist-info/LICENSE
tiles_util-1.1.0.dist-info/METADATA
tiles_util-1.1.0.dist-info/WHEEL
tiles_util-1.1.0.dist-info/entry_points.txt
tiles_util-1.1.0.dist-info/top_level.txt
tiles_util-1.1.0.dist-info/RECORD
