Metadata-Version: 2.1
Name: tiles-util
Version: 1.1.0
Summary: Vector Tiles Utilities
Home-page: https://github.com/thangqd/tiles_util
Author: Thang Quach
Author-email: quachdongthang@gmail.com
Classifier: Programming Language :: Python :: 3
Classifier: Environment :: Console
Classifier: Topic :: Scientific/Engineering :: GIS
Classifier: License :: OSI Approved :: MIT License
Classifier: Operating System :: OS Independent
License-File: LICENSE
Requires-Dist: tqdm ~=4.66.2
Requires-Dist: boto3 ~=1.34.72
Requires-Dist: requests ~=2.31.0
Requires-Dist: click ~=8.1.7
Requires-Dist: fiona ~=1.9.4
Requires-Dist: shapely ~=2.0.1
Requires-Dist: osmium ~=3.7.0
Requires-Dist: protobuf ~=5.26.1
